odoo/addons/account_edi_no_autocreate_partner/README.rst
odoo/addons/account_edi_no_autocreate_partner/__init__.py
odoo/addons/account_edi_no_autocreate_partner/__manifest__.py
odoo/addons/account_edi_no_autocreate_partner/data/res_partner.xml
odoo/addons/account_edi_no_autocreate_partner/i18n/account_edi_no_autocreate_partner.pot
odoo/addons/account_edi_no_autocreate_partner/i18n/it.po
odoo/addons/account_edi_no_autocreate_partner/models/__init__.py
odoo/addons/account_edi_no_autocreate_partner/models/account_edi_format.py
odoo/addons/account_edi_no_autocreate_partner/models/account_move.py
odoo/addons/account_edi_no_autocreate_partner/models/res_partner.py
odoo/addons/account_edi_no_autocreate_partner/readme/CONTRIBUTORS.md
odoo/addons/account_edi_no_autocreate_partner/readme/DESCRIPTION.md
odoo/addons/account_edi_no_autocreate_partner/static/description/icon.png
odoo/addons/account_edi_no_autocreate_partner/static/description/index.html
odoo/addons/account_edi_no_autocreate_partner/tests/__init__.py
odoo/addons/account_edi_no_autocreate_partner/tests/test_account_edi_no_autocreate_partner.py
odoo_addon_account_edi_no_autocreate_partner-16.0.1.0.0.4.dist-info/METADATA
odoo_addon_account_edi_no_autocreate_partner-16.0.1.0.0.4.dist-info/WHEEL
odoo_addon_account_edi_no_autocreate_partner-16.0.1.0.0.4.dist-info/top_level.txt
odoo_addon_account_edi_no_autocreate_partner-16.0.1.0.0.4.dist-info/RECORD
